{
  "b": 209,
  "disableInputWhenNotFocused": true,
  "mangledName": "X_32_45_45_45_324_462_32_45_32JOGO_32DA_32MEM_211RIA_32_40Final_41_32_45_32cartas_32coletadas",
  "name": "X --- 4.2 - JOGO DA MEMÓRIA (Final) - cartas coletadas",
  "r": 209,
  "standardSortMethod": true,
  "stopSoundsOnStartup": true,
  "title": "",
  "v": 209,
  "uiSettings": {
    "grid": false,
    "gridType": "rectangular",
    "gridWidth": 32,
    "gridHeight": 32,
    "gridOffsetX": 0,
    "gridOffsetY": 0,
    "gridColor": 10401023,
    "gridAlpha": 0.8,
    "snap": false,
    "zoomFactor": 0.3784561861455743,
    "windowMask": false
  },
  "objectsGroups": [],
  "variables": [
    {
      "name": "NextLevel",
      "type": "string",
      "value": "Level3"
    }
  ],
  "instances": [
    {
      "angle": 0,
      "customSize": true,
      "depth": 5,
      "height": 332,
      "layer": "",
      "name": "card_A",
      "persistentUuid": "2d0b0e8b-56c3-497a-9259-51baa5b14b4a",
      "width": 332,
      "x": 383,
      "y": 278,
      "zOrder": 2,
      "numberProperties": [],
      "stringProperties": [],
      "initialVariables": []
    },
    {
      "angle": 0,
      "customSize": true,
      "depth": 1,
      "height": 59,
      "layer": "",
      "name": "DescriçãoText",
      "persistentUuid": "b905b826-43f1-40b8-86f9-2e351f053ee3",
      "width": 256,
      "x": 258,
      "y": 472,
      "zOrder": 3,
      "numberProperties": [],
      "stringProperties": [],
      "initialVariables": []
    },
    {
      "angle": 0,
      "customSize": true,
      "depth": 4,
      "height": 343,
      "layer": "",
      "name": "card_G",
      "persistentUuid": "48bc7946-c268-42cd-a6fd-246ab7c89c25",
      "width": 343,
      "x": 913,
      "y": 280,
      "zOrder": 4,
      "numberProperties": [],
      "stringProperties": [],
      "initialVariables": []
    },
    {
      "angle": 0,
      "customSize": true,
      "depth": 1,
      "height": 86,
      "keepRatio": true,
      "layer": "",
      "name": "LevelSelectionBtn",
      "persistentUuid": "7fde5684-dd38-46c9-81b0-b1df6ce98a7a",
      "width": 206,
      "x": 1039,
      "y": 580,
      "zOrder": 5,
      "numberProperties": [],
      "stringProperties": [],
      "initialVariables": []
    }
  ],
  "objects": [
    {
      "assetStoreId": "02cb22c03a7c7f9262819832f0fea819fc5021f2b7a8854eb99d6ff20f180d66",
      "name": "WhiteSleekButton",
      "type": "PanelSpriteButton::PanelSpriteButton",
      "variables": [],
      "effects": [],
      "behaviors": [],
      "content": {
        "BottomPadding": 31,
        "TopPadding": 5,
        "LeftPadding": 12,
        "RightPadding": 12,
        "PressedLabelOffsetY": 6
      },
      "childrenContent": {
        "Hovered": {
          "bottomMargin": 55,
          "height": 128,
          "leftMargin": 40,
          "rightMargin": 40,
          "texture": "White Sleek Button_Hovered.png",
          "tiled": false,
          "topMargin": 37,
          "width": 256
        },
        "Idle": {
          "bottomMargin": 55,
          "height": 128,
          "leftMargin": 40,
          "rightMargin": 40,
          "texture": "White Sleek Button_Idle.png",
          "tiled": false,
          "topMargin": 37,
          "width": 256
        },
        "Label": {
          "bold": false,
          "italic": false,
          "smoothed": true,
          "underlined": false,
          "string": "NEXT",
          "font": "WorkSans-Regular.ttf",
          "textAlignment": "center",
          "characterSize": 60,
          "color": {
            "b": 95,
            "g": 23,
            "r": 6
          },
          "content": {
            "bold": false,
            "isOutlineEnabled": false,
            "isShadowEnabled": false,
            "italic": false,
            "outlineColor": "255;255;255",
            "outlineThickness": 2,
            "shadowAngle": 90,
            "shadowBlurRadius": 2,
            "shadowColor": "0;0;0",
            "shadowDistance": 4,
            "shadowOpacity": 127,
            "smoothed": true,
            "underlined": false,
            "text": "NEXT",
            "font": "WorkSans-Regular.ttf",
            "textAlignment": "center",
            "verticalTextAlignment": "top",
            "characterSize": 60,
            "color": "6;23;95"
          }
        },
        "Pressed": {
          "bottomMargin": 55,
          "height": 128,
          "leftMargin": 40,
          "rightMargin": 40,
          "texture": "White Sleek Button_Pressed.png",
          "tiled": false,
          "topMargin": 37,
          "width": 256
        }
      }
    },
    {
      "assetStoreId": "0d2644a425931f79026065835332ea795353d1f99fcd6ccd47ab7927bd0f35ed",
      "name": "BlackSquareDecoratedButton",
      "type": "PanelSpriteButton::PanelSpriteButton",
      "variables": [],
      "effects": [],
      "behaviors": [],
      "content": {
        "LeftPadding": 16,
        "RightPadding": 16,
        "PressedLabelOffsetY": 6,
        "BottomPadding": 24,
        "TopPadding": 24,
        "HoveredFadeOutDuration": 0.25
      },
      "childrenContent": {
        "Hovered": {
          "bottomMargin": 22,
          "height": 64,
          "leftMargin": 16,
          "rightMargin": 16,
          "texture": "Black Square Decorated Button_Hovered.png",
          "tiled": true,
          "topMargin": 16,
          "width": 192
        },
        "Idle": {
          "bottomMargin": 22,
          "height": 64,
          "leftMargin": 16,
          "rightMargin": 16,
          "texture": "Black Square Decorated Button_Idle.png",
          "tiled": true,
          "topMargin": 16,
          "width": 192
        },
        "Label": {
          "bold": false,
          "italic": false,
          "smoothed": true,
          "underlined": false,
          "string": "Button",
          "font": "mononoki-Regular.ttf",
          "textAlignment": "center",
          "characterSize": 26,
          "color": {
            "b": 255,
            "g": 255,
            "r": 255
          },
          "content": {
            "bold": false,
            "isOutlineEnabled": false,
            "isShadowEnabled": false,
            "italic": false,
            "outlineColor": "255;255;255",
            "outlineThickness": 2,
            "shadowAngle": 90,
            "shadowBlurRadius": 2,
            "shadowColor": "0;0;0",
            "shadowDistance": 4,
            "shadowOpacity": 127,
            "smoothed": true,
            "underlined": false,
            "text": "Button",
            "font": "mononoki-Regular.ttf",
            "textAlignment": "center",
            "verticalTextAlignment": "top",
            "characterSize": 26,
            "color": "255;255;255"
          }
        },
        "Pressed": {
          "bottomMargin": 16,
          "height": 64,
          "leftMargin": 16,
          "rightMargin": 16,
          "texture": "Black Square Decorated Button_Pressed.png",
          "tiled": true,
          "topMargin": 22,
          "width": 192
        }
      }
    },
    {
      "adaptCollisionMaskAutomatically": false,
      "assetStoreId": "",
      "name": "card_A",
      "type": "Sprite",
      "updateIfNotVisible": false,
      "variables": [
        {
          "name": "id",
          "type": "string",
          "value": "crab"
        }
      ],
      "effects": [],
      "behaviors": [
        {
          "name": "Tween",
          "type": "Tween::TweenBehavior"
        }
      ],
      "animations": [
        {
          "name": "front",
          "useMultipleDirections": false,
          "directions": [
            {
              "looping": false,
              "metadata": "{\"pskl\":{}}",
              "timeBetweenFrames": 0.08,
              "sprites": [
                {
                  "hasCustomCollisionMask": false,
                  "image": "front3",
                  "points": [],
                  "originPoint": {
                    "name": "origine",
                    "x": 32,
                    "y": 32
                  },
                  "centerPoint": {
                    "automatic": true,
                    "name": "centre",
                    "x": 32,
                    "y": 32
                  },
                  "customCollisionMask": []
                }
              ]
            }
          ]
        },
        {
          "name": "back",
          "useMultipleDirections": false,
          "directions": [
            {
              "looping": false,
              "metadata": "{\"pskl\":{}}",
              "timeBetweenFrames": 0.08,
              "sprites": [
                {
                  "hasCustomCollisionMask": false,
                  "image": "back9",
                  "points": [],
                  "originPoint": {
                    "name": "origine",
                    "x": 32,
                    "y": 32
                  },
                  "centerPoint": {
                    "automatic": true,
                    "name": "centre",
                    "x": 32,
                    "y": 32
                  },
                  "customCollisionMask": []
                }
              ]
            }
          ]
        }
      ]
    },
    {
      "assetStoreId": "",
      "bold": false,
      "italic": false,
      "name": "DescriçãoText",
      "smoothed": true,
      "type": "TextObject::Text",
      "underlined": false,
      "variables": [],
      "effects": [],
      "behaviors": [],
      "string": "Text abcdefg",
      "font": "",
      "textAlignment": "left",
      "characterSize": 20,
      "color": {
        "b": 0,
        "g": 0,
        "r": 0
      },
      "content": {
        "bold": false,
        "isOutlineEnabled": false,
        "isShadowEnabled": false,
        "italic": false,
        "outlineColor": "255;255;255",
        "outlineThickness": 2,
        "shadowAngle": 90,
        "shadowBlurRadius": 2,
        "shadowColor": "0;0;0",
        "shadowDistance": 4,
        "shadowOpacity": 127,
        "smoothed": true,
        "underlined": false,
        "text": "Text abcdefg",
        "font": "",
        "textAlignment": "left",
        "verticalTextAlignment": "top",
        "characterSize": 20,
        "color": "0;0;0"
      }
    },
    {
      "adaptCollisionMaskAutomatically": false,
      "assetStoreId": "",
      "name": "card_G",
      "type": "Sprite",
      "updateIfNotVisible": false,
      "variables": [
        {
          "name": "id",
          "type": "string",
          "value": "plasticbag"
        }
      ],
      "effects": [],
      "behaviors": [
        {
          "name": "Tween",
          "type": "Tween::TweenBehavior"
        }
      ],
      "animations": [
        {
          "name": "front",
          "useMultipleDirections": false,
          "directions": [
            {
              "looping": false,
              "metadata": "{\"pskl\":{}}",
              "timeBetweenFrames": 0.08,
              "sprites": [
                {
                  "hasCustomCollisionMask": false,
                  "image": "front10",
                  "points": [],
                  "originPoint": {
                    "name": "origine",
                    "x": 32,
                    "y": 32
                  },
                  "centerPoint": {
                    "automatic": true,
                    "name": "centre",
                    "x": 32,
                    "y": 32
                  },
                  "customCollisionMask": []
                }
              ]
            }
          ]
        },
        {
          "name": "back",
          "useMultipleDirections": false,
          "directions": [
            {
              "looping": false,
              "metadata": "{\"pskl\":{}}",
              "timeBetweenFrames": 0.08,
              "sprites": [
                {
                  "hasCustomCollisionMask": false,
                  "image": "back15",
                  "points": [],
                  "originPoint": {
                    "name": "origine",
                    "x": 32,
                    "y": 32
                  },
                  "centerPoint": {
                    "automatic": true,
                    "name": "centre",
                    "x": 32,
                    "y": 32
                  },
                  "customCollisionMask": []
                }
              ]
            }
          ]
        }
      ]
    },
    {
      "adaptCollisionMaskAutomatically": false,
      "assetStoreId": "",
      "name": "LevelSelectionBtn",
      "type": "Sprite",
      "updateIfNotVisible": false,
      "variables": [],
      "effects": [],
      "behaviors": [],
      "animations": [
        {
          "name": "",
          "useMultipleDirections": false,
          "directions": [
            {
              "looping": false,
              "timeBetweenFrames": 0.08,
              "sprites": [
                {
                  "hasCustomCollisionMask": false,
                  "image": "Green Button_Hovered.png",
                  "points": [],
                  "originPoint": {
                    "name": "origine",
                    "x": 0,
                    "y": 0
                  },
                  "centerPoint": {
                    "automatic": true,
                    "name": "centre",
                    "x": 0,
                    "y": 0
                  },
                  "customCollisionMask": []
                }
              ]
            }
          ]
        }
      ]
    }
  ],
  "objectsFolderStructure": {
    "folderName": "__ROOT",
    "children": [
      {
        "objectName": "WhiteSleekButton"
      },
      {
        "objectName": "LevelSelectionBtn"
      },
      {
        "objectName": "card_A"
      },
      {
        "objectName": "card_G"
      },
      {
        "objectName": "BlackSquareDecoratedButton"
      },
      {
        "objectName": "DescriçãoText"
      }
    ]
  },
  "events": [
    {
      "colorB": 228,
      "colorG": 176,
      "colorR": 74,
      "creationTime": 0,
      "name": "lINK BOTÕES -mudar de cena",
      "source": "",
      "type": "BuiltinCommonInstructions::Group",
      "events": [
        {
          "type": "BuiltinCommonInstructions::Comment",
          "color": {
            "b": 109,
            "g": 230,
            "r": 255,
            "textB": 0,
            "textG": 0,
            "textR": 0
          },
          "comment": "Eu adiciono o \"link\" para que ao apertar no botão mude a cena para a \"cena\" do \"jogo\"."
        },
        {
          "colorB": 228,
          "colorG": 176,
          "colorR": 74,
          "creationTime": 0,
          "name": "Botão link ",
          "source": "",
          "type": "BuiltinCommonInstructions::Group",
          "events": [
            {
              "type": "BuiltinCommonInstructions::Comment",
              "color": {
                "b": 109,
                "g": 230,
                "r": 255,
                "textB": 0,
                "textG": 0,
                "textR": 0
              },
              "comment": ""
            },
            {
              "type": "BuiltinCommonInstructions::Standard",
              "conditions": [
                {
                  "type": {
                    "value": "SourisSurObjet"
                  },
                  "parameters": [
                    "WhiteSleekButton",
                    "",
                    "",
                    ""
                  ]
                }
              ],
              "actions": [],
              "events": [
                {
                  "type": "BuiltinCommonInstructions::Standard",
                  "conditions": [
                    {
                      "type": {
                        "value": "MouseButtonReleased"
                      },
                      "parameters": [
                        "",
                        "Left"
                      ]
                    }
                  ],
                  "actions": [
                    {
                      "type": {
                        "value": "Scene"
                      },
                      "parameters": [
                        "",
                        "\"X1 🗺- mapa  -  (1-4) ZUMA\"",
                        ""
                      ]
                    }
                  ]
                }
              ]
            }
          ],
          "parameters": []
        }
      ],
      "parameters": []
    },
    {
      "type": "BuiltinCommonInstructions::Standard",
      "conditions": [],
      "actions": []
    }
  ],
  "layers": [
    {
      "ambientLightColorB": 200,
      "ambientLightColorG": 200,
      "ambientLightColorR": 200,
      "camera3DFarPlaneDistance": 10000,
      "camera3DFieldOfView": 45,
      "camera3DNearPlaneDistance": 3,
      "cameraType": "",
      "followBaseLayerCamera": false,
      "isLightingLayer": false,
      "isLocked": false,
      "name": "",
      "renderingType": "",
      "visibility": true,
      "cameras": [
        {
          "defaultSize": true,
          "defaultViewport": true,
          "height": 0,
          "viewportBottom": 1,
          "viewportLeft": 0,
          "viewportRight": 1,
          "viewportTop": 0,
          "width": 0
        }
      ],
      "effects": [
        {
          "effectType": "Scene3D::HemisphereLight",
          "name": "3D Light",
          "doubleParameters": {
            "elevation": 45,
            "intensity": 1,
            "rotation": 0
          },
          "stringParameters": {
            "groundColor": "64;64;64",
            "skyColor": "255;255;255",
            "top": "Y-"
          },
          "booleanParameters": {}
        }
      ]
    }
  ],
  "behaviorsSharedData": [
    {
      "name": "Animation",
      "type": "AnimatableCapability::AnimatableBehavior"
    },
    {
      "name": "Effect",
      "type": "EffectCapability::EffectBehavior"
    },
    {
      "name": "Flippable",
      "type": "FlippableCapability::FlippableBehavior"
    },
    {
      "name": "Opacity",
      "type": "OpacityCapability::OpacityBehavior"
    },
    {
      "name": "Resizable",
      "type": "ResizableCapability::ResizableBehavior"
    },
    {
      "name": "Scale",
      "type": "ScalableCapability::ScalableBehavior"
    },
    {
      "name": "Text",
      "type": "TextContainerCapability::TextContainerBehavior"
    },
    {
      "name": "Tween",
      "type": "Tween::TweenBehavior"
    }
  ]
}